registers/counter/counter.v
module counter (
    clk,
    reset,
    enable,
    count
);

    input clk, reset, enable;
    output reg [7:0] count;

    always @(posedge clk or posedge reset) begin
        if (reset) begin
            count <= 8'b0;
        end else if (enable) begin
            count <= count + 1;
        end
    end

endmodule

registers/counter/counter_tb.v
module counter_tb;

    reg clk, enable, reset;
    wire [0:7] count;

    counter uut (
        .clk(clk),
        .enable(enable),
        .reset(reset),
        .count(count)
    );

    initial clk = 0;
    always #5 clk = ~clk;

    initial begin
        $dumpfile("counter_wave.vcd");
        $dumpvars(0, counter_tb);

        reset  = 1;
        enable = 0;

        #10 reset = 0;
        #10 enable = 1;

        #100;

        enable = 0;
        #20;

        reset = 1;
        #10 reset = 0;

        enable = 1;
        #50;

        $finish;
    end

endmodule

registers/counter/counter_wave.vcd
$date
	Sun Sep 28 23:15:36 2025
$end
$version
	Icarus Verilog
$end
$timescale
	1s
$end
$scope module counter_tb $end
$var wire 8 ! count [0:7] $end
$var reg 1 " clk $end
$var reg 1 # enable $end
$var reg 1 $ reset $end
$scope module uut $end
$var wire 1 " clk $end
$var wire 1 # enable $end
$var wire 1 $ reset $end
$var reg 8 % count [0:7] $end
$upscope $end
$upscope $end
$enddefinitions $end
$comment Show the parameter values. $end
$dumpall
$end
#0
$dumpvars
b0 %
1$
0#
0"
b0 !
$end
#5
1"
#10
0"
0$
#15
1"
#20
0"
1#
#25
b1 !
b1 %
1"
#30
0"
#35
b10 !
b10 %
1"
#40
0"
#45
b11 !
b11 %
1"
#50
0"
#55
b100 !
b100 %
1"
#60
0"
#65
b101 !
b101 %
1"
#70
0"
#75
b110 !
b110 %
1"
#80
0"
#85
b111 !
b111 %
1"
#90
0"
#95
b1000 !
b1000 %
1"
#100
0"
#105
b1001 !
b1001 %
1"
#110
0"
#115
b1010 !
b1010 %
1"
#120
0"
0#
#125
1"
#130
0"
#135
1"
#140
b0 !
b0 %
0"
1$
#145
1"
#150
0"
1#
0$
#155
b1 !
b1 %
1"
#160
0"
#165
b10 !
b10 %
1"
#170
0"
#175
b11 !
b11 %
1"
#180
0"
#185
b100 !
b100 %
1"
#190
0"
#195
b101 !
b101 %
1"
