full_subtractor/full_subtractor.v
module full_subtractor (
    a,b,bin,diff,bout
);
    input a,b,bin;
    output reg diff,bout;

    // assign diff = a ^ b ^ bin;
    // assign bout = (~a * b ) | (~a * bin) | (b * bin);

    always @(a,b,bin) begin
        diff = a ^ b ^ bin;
        bout = (~a * b ) | (~a * bin) | (b * bin); 
    end
endmodule

subtractors/full_subtractor/full_subtractor_tb.v
module full_subtractor_tb;
    reg a,b,bin;
    wire diff,bout;

    full_subtractor uut(.a(a),.b(b),.bin(bin),.diff(diff),.bout(bout));

    initial begin
        $dumpfile("full_subtractor_wave.vcd");
        $dumpvars(0,full_subtractor_tb);
        
        $monitor("a = %b | b = %b | bin = %b | difference = %b | bout = %b",a,b,bin,diff,bout);

        a = 0; b = 0; bin = 0; #5;
        a = 0; b = 0; bin = 1; #5;
        a = 0; b = 1; bin = 0; #5;
        a = 0; b = 1; bin = 1; #5;
        a = 1; b = 0; bin = 0; #5;
        a = 1; b = 0; bin = 1; #5;
        a = 1; b = 1; bin = 0; #5;
        a = 1; b = 1; bin = 1; #5;

        $finish;
    end
endmodule

full_subtractor/full_subtractor_wave.vcd
$date
	Thu Dec 18 12:40:17 2025
$end
$version
	Icarus Verilog
$end
$timescale
	1s
$end
$scope module full_subtractor_tb $end
$var wire 1 ! diff $end
$var wire 1 " bout $end
$var reg 1 # a $end
$var reg 1 $ b $end
$var reg 1 % bin $end
$scope module uut $end
$var wire 1 # a $end
$var wire 1 $ b $end
$var wire 1 % bin $end
$var reg 1 " bout $end
$var reg 1 ! diff $end
$upscope $end
$upscope $end
$enddefinitions $end
$comment Show the parameter values. $end
$dumpall
$end
#0
$dumpvars
0%
0$
0#
0"
0!
$end
#5
1"
1!
1%
#10
0%
1$
#15
0!
1%
#20
0"
1!
0%
0$
1#
#25
0!
1%
#30
0%
1$
#35
1"
1!
1%
