expressions/exp1/exp1.v
module exp1 (
    a,b,c,y
);
    input a,b,c;
    output reg y;

    always @(a,b,c) begin
        y = (a | (b & c));
    end
endmodule

expressions/exp1/exp1_tb.v
module exp1_tb;
    reg a,b,c;
    wire y;

    exp1 uut(a,b,c,y);

    initial begin
        $dumpfile("exp1_wave.vcd");
        $dumpvars(0,exp1_tb);

        $monitor("a = %b | b = %b | c = %b | y = %b",a,b,c,y);

        a = 0; b = 0; c = 0; #5;
        a = 0; b = 0; c = 1; #5;
        a = 0; b = 1; c = 0; #5;
        a = 0; b = 1; c = 1; #5;
        a = 1; b = 0; c = 0; #5;
        a = 1; b = 0; c = 1; #5;
        a = 1; b = 1; c = 0; #5;
        a = 1; b = 1; c = 1; #5;

        $finish;
    end
endmodule

expressions/exp1/exp1_wave.vcd
$date
	Fri Dec 19 10:15:12 2025
$end
$version
	Icarus Verilog
$end
$timescale
	1s
$end
$scope module exp1_tb $end
$var wire 1 ! y $end
$var reg 1 " a $end
$var reg 1 # b $end
$var reg 1 $ c $end
$scope module uut $end
$var wire 1 " a $end
$var wire 1 # b $end
$var wire 1 $ c $end
$var reg 1 ! y $end
$upscope $end
$upscope $end
$enddefinitions $end
$comment Show the parameter values. $end
$dumpall
$end
#0
$dumpvars
0$
0#
0"
0!
$end
#5
1$
#10
0$
1#
#15
1!
1$
#20
0$
0#
1"
#25
1$
#30
0$
1#
#35
1$
