parameters/param_subtractor/param_subtractor.v
module param_subtractor #(
    parameter SIZE = 1
) (
    a,
    b,
    diff,
    borrow
);
    input [SIZE -1 : 0] a, b;
    output [SIZE -1 : 0] diff;
    output borrow;

    assign borrow = a < b;
    assign diff   = a - b;
endmodule

parameters/param_subtractor/param_subtractor_tb.v
module param_subtractor_tb;
    reg [1:0] a, b;
    wire [1:0] diff;
    wire borrow;

    param_subtractor #(
        .SIZE(2)
    ) uut (
        a,
        b,
        diff,
        borrow
    );

    initial begin
        $dumpfile("param_subtractor_wave.vcd");
        $dumpvars(0, param_subtractor_tb);

        $monitor("a = %b | b = %b | diff = %b | borrow = %b", a, b, diff,
                 borrow);


        a = 2'b00;
        b = 2'b00;
        #10;

        a = 2'b01;
        b = 2'b00;
        #10;

        a = 2'b01;
        b = 2'b01;
        #10;

        a = 2'b00;
        b = 2'b01;
        #10;

        a = 2'b10;
        b = 2'b01;
        #10;

        a = 2'b01;
        b = 2'b10;
        #10;

        a = 2'b11;
        b = 2'b01;
        #10;

        a = 2'b01;
        b = 2'b11;
        #10;

        a = 2'b11;
        b = 2'b11;
        #10;

        $finish;
    end
endmodule

parameters/param_subtractor/param_subtractor_wave.vcd
$date
	Tue Jan 27 20:14:11 2026
$end
$version
	Icarus Verilog
$end
$timescale
	1s
$end
$scope module param_subtractor_tb $end
$var wire 2 ! diff [1:0] $end
$var wire 1 " borrow $end
$var reg 2 # a [1:0] $end
$var reg 2 $ b [1:0] $end
$scope module uut $end
$var wire 2 % a [1:0] $end
$var wire 2 & b [1:0] $end
$var wire 2 ' diff [1:0] $end
$var wire 1 " borrow $end
$var parameter 32 ( SIZE $end
$upscope $end
$upscope $end
$enddefinitions $end
$comment Show the parameter values. $end
$dumpall
b10 (
$end
#0
$dumpvars
b0 '
b0 &
b0 %
b0 $
b0 #
0"
b0 !
$end
#10
b1 !
b1 '
b1 #
b1 %
#20
b0 !
b0 '
b1 $
b1 &
#30
1"
b11 !
b11 '
b0 #
b0 %
#40
0"
b1 !
b1 '
b10 #
b10 %
#50
1"
b10 $
b10 &
b11 !
b11 '
b1 #
b1 %
#60
b1 $
b1 &
0"
b10 !
b10 '
b11 #
b11 %
#70
1"
b11 $
b11 &
b10 !
b10 '
b1 #
b1 %
#80
0"
b0 !
b0 '
b11 #
b11 %
