parameters/param_memory/param_memory.v
module param_memory #(
    parameter SIZE  = 256,
    parameter WIDTH = 8
) (
    clk,
    write_enable,
    address,
    data_in,
    data_out
);
    input clk, write_enable;
    input [7:0] address, data_in;
    output reg [7:0] data_out;
    reg [WIDTH -1 : 0] memory[0:SIZE-1];

    always @(posedge clk) begin
        if (write_enable) memory[address] = data_in;
        else data_out <= memory[address];
    end
endmodule

parameters/param_memory/param_memory_tb.v
module param_memory_tb;
    reg clk, write_enable;
    reg [7:0] data_in, address;
    wire [7:0] data_out;

    param_memory uut (
        clk,
        write_enable,
        address,
        data_in,
        data_out
    );

    initial begin
        clk = 0;
        forever #5 clk = ~clk;
    end

    initial begin
        $dumpfile("param_memory_wave.vcd");
        $dumpvars(0, param_memory_tb);

        write_enable = 0;
        data_in = 0;
        address = 0;
        #10;

        write_enable = 1;
        address = 8'd05;
        data_in = 8'd45;
        $display("Written data = %d at address = %d", data_in, address);
        #10;

        address = 8'd00;
        data_in = 8'd77;
        $display("Written data = %d at address = %d", data_in, address);
        #10;

        address = 8'd03;
        data_in = 8'd32;
        $display("Written data = %d at address = %d", data_in, address);
        #10;

        write_enable = 0;

        address = 8'd05;
        #10;
        $display("Read from address = %d value = %d", address, data_out);
        #10;

        address = 8'd00;
        #10;
        $display("Read from address = %d value = %d", address, data_out);
        #10;

        address = 8'd03;
        #10;
        $display("Read from address = %d value = %d", address, data_out);
        #10;

        address = 8'd10;
        #10;
        $display("Read from address = %d value = %d", address, data_out);
        #10;

        write_enable = 1;
        address = 8'd20;
        data_in = 8'd12;
        $display("Written data = %d at address = %d, Read from address = %d",
                 data_in, address, data_out);
        #10;

        write_enable = 0;
        #10;
        $display("Read from address = %d value = %d", address, data_out);

        $finish;

    end
endmodule

parameters/param_memory/param_memory_wave.vcd
$date
	Sat Jan 31 00:42:12 2026
$end
$version
	Icarus Verilog
$end
$timescale
	1s
$end
$scope module param_memory_tb $end
$var wire 8 ! data_out [7:0] $end
$var reg 8 " address [7:0] $end
$var reg 1 # clk $end
$var reg 8 $ data_in [7:0] $end
$var reg 1 % write_enable $end
$scope module uut $end
$var wire 8 & address [7:0] $end
$var wire 1 # clk $end
$var wire 8 ' data_in [7:0] $end
$var wire 1 % write_enable $end
$var parameter 32 ( SIZE $end
$var parameter 32 ) WIDTH $end
$var reg 8 * data_out [7:0] $end
$upscope $end
$upscope $end
$enddefinitions $end
$comment Show the parameter values. $end
$dumpall
b1000 )
b100000000 (
$end
#0
$dumpvars
bx *
b0 '
b0 &
0%
b0 $
0#
b0 "
bx !
$end
#5
1#
#10
0#
b101101 $
b101101 '
b101 "
b101 &
1%
#15
1#
#20
0#
b1001101 $
b1001101 '
b0 "
b0 &
#25
1#
#30
0#
b100000 $
b100000 '
b11 "
b11 &
#35
1#
#40
0#
b101 "
b101 &
0%
#45
b101101 !
b101101 *
1#
#50
0#
#55
1#
#60
0#
b0 "
b0 &
#65
b1001101 !
b1001101 *
1#
#70
0#
#75
1#
#80
0#
b11 "
b11 &
#85
b100000 !
b100000 *
1#
#90
0#
#95
1#
#100
0#
b1010 "
b1010 &
#105
bx !
bx *
1#
#110
0#
#115
1#
#120
0#
b1100 $
b1100 '
b10100 "
b10100 &
1%
#125
1#
#130
0#
0%
#135
b1100 !
b1100 *
1#
