aoi/aoi.v
module aoi (
    a,b,c,d,y
);
    input a,b,c,d;
    output y;

    assign y = !((a&b) | (c&d));

endmodule

aoi/aoi_tb.v
module aoi_tb;

    reg a,b,c,d;
    wire y;

    aoi dut(.a(a),.b(b),.c(c),.d(d),.y(y));

    initial begin
        
        $dumpfile("aoi_wave.vcd");
        $dumpvars(0,aoi_tb);

        a = 0; b = 0; c = 0; d = 0; #5;
        a = 0; b = 0; c = 0; d = 1; #5;
        a = 0; b = 0; c = 1; d = 0; #5;
        a = 0; b = 0; c = 1; d = 1; #5;
        a = 0; b = 1; c = 0; d = 0; #5;
        a = 0; b = 1; c = 0; d = 1; #5;
        a = 0; b = 1; c = 1; d = 0; #5;
        a = 0; b = 1; c = 1; d = 1; #5;
        a = 1; b = 0; c = 0; d = 0; #5;
        a = 1; b = 0; c = 0; d = 1; #5;
        a = 1; b = 0; c = 1; d = 0; #5;
        a = 1; b = 0; c = 1; d = 1; #5;
        a = 1; b = 1; c = 0; d = 0; #5;
        a = 1; b = 1; c = 0; d = 1; #5;
        a = 1; b = 1; c = 1; d = 0; #5;
        a = 1; b = 1; c = 1; d = 1; #5;
        $finish;
    end

    initial begin
        $monitor("Time = %0t | a = %b | b = %b | c = %b | d = %d",$time,a,b,c,d);
    end

endmodule

aoi/aoi_wave.vcd
$date
	Sun Aug 31 18:12:08 2025
$end
$version
	Icarus Verilog
$end
$timescale
	1s
$end
$scope module aoi_tb $end
$var wire 1 ! y $end
$var reg 1 " a $end
$var reg 1 # b $end
$var reg 1 $ c $end
$var reg 1 % d $end
$scope module dut $end
$var wire 1 " a $end
$var wire 1 # b $end
$var wire 1 $ c $end
$var wire 1 % d $end
$var wire 1 ! y $end
$upscope $end
$upscope $end
$enddefinitions $end
$comment Show the parameter values. $end
$dumpall
$end
#0
$dumpvars
0%
0$
0#
0"
1!
$end
#5
1%
#10
0%
1$
#15
0!
1%
#20
1!
0%
0$
1#
#25
1%
#30
0%
1$
#35
0!
1%
#40
1!
0%
0$
0#
1"
#45
1%
#50
0%
1$
#55
0!
1%
#60
0%
0$
1#
#65
1%
#70
0%
1$
#75
1%
