registers/up_down_counter/up_down_counter.v
module up_down_counter (
    clk,
    reset,
    up_down,
    count
);
    input clk, reset, up_down;
    output reg [0:3] count;

    always @(posedge clk or posedge reset) begin
        if (reset) begin
            count <= 4'b0000;
        end else begin
            if (up_down) begin
                count <= count + 1;
            end else begin
                count <= count - 1;
            end
        end
    end
endmodule

registers/up_down_counter/up_down_counter_tb.v
module up_down_counter_tb;
    reg clk, reset, up_down;
    wire [0:3] count;

    up_down_counter uut (
        clk,
        reset,
        up_down,
        count
    );

    initial clk = 0;
    always #5 clk = ~clk;

    initial begin
        $dumpfile("up_down_counter_wave.vcd");
        $dumpvars(0, up_down_counter_tb);

        $monitor("clk = %b | reset = %b | up_down = %b | count = %b", clk,
                 reset, up_down, count);

        reset   = 1;
        up_down = 0;
        #10;
        reset = 0;
        #10;

        up_down = 1;
        #100;

        up_down = 0;
        #100;

        up_down = 1;
        #30;
        up_down = 0;
        #20;
        up_down = 1;
        #50;

        $finish;
    end
endmodule

registers/up_down_counter/up_down_counter_wave.vcd
$date
	Mon Jan 26 00:48:03 2026
$end
$version
	Icarus Verilog
$end
$timescale
	1s
$end
$scope module up_down_counter_tb $end
$var wire 4 ! count [0:3] $end
$var reg 1 " clk $end
$var reg 1 # reset $end
$var reg 1 $ up_down $end
$scope module uut $end
$var wire 1 " clk $end
$var wire 1 # reset $end
$var wire 1 $ up_down $end
$var reg 4 % count [0:3] $end
$upscope $end
$upscope $end
$enddefinitions $end
$comment Show the parameter values. $end
$dumpall
$end
#0
$dumpvars
b0 %
0$
1#
0"
b0 !
$end
#5
1"
#10
0"
0#
#15
b1111 !
b1111 %
1"
#20
0"
1$
#25
b0 !
b0 %
1"
#30
0"
#35
b1 !
b1 %
1"
#40
0"
#45
b10 !
b10 %
1"
#50
0"
#55
b11 !
b11 %
1"
#60
0"
#65
b100 !
b100 %
1"
#70
0"
#75
b101 !
b101 %
1"
#80
0"
#85
b110 !
b110 %
1"
#90
0"
#95
b111 !
b111 %
1"
#100
0"
#105
b1000 !
b1000 %
1"
#110
0"
#115
b1001 !
b1001 %
1"
#120
0"
0$
#125
b1000 !
b1000 %
1"
#130
0"
#135
b111 !
b111 %
1"
#140
0"
#145
b110 !
b110 %
1"
#150
0"
#155
b101 !
b101 %
1"
#160
0"
#165
b100 !
b100 %
1"
#170
0"
#175
b11 !
b11 %
1"
#180
0"
#185
b10 !
b10 %
1"
#190
0"
#195
b1 !
b1 %
1"
#200
0"
#205
b0 !
b0 %
1"
#210
0"
#215
b1111 !
b1111 %
1"
#220
0"
1$
#225
b0 !
b0 %
1"
#230
0"
#235
b1 !
b1 %
1"
#240
0"
#245
b10 !
b10 %
1"
#250
0"
0$
#255
b1 !
b1 %
1"
#260
0"
#265
b0 !
b0 %
1"
#270
0"
1$
#275
b1 !
b1 %
1"
#280
0"
#285
b10 !
b10 %
1"
#290
0"
#295
b11 !
b11 %
1"
#300
0"
#305
b100 !
b100 %
1"
#310
0"
#315
b101 !
b101 %
1"
