expressions/exp2/exp2.v
module exp2 (
    a,b,c,d,y
);
    input a,b,c,d;
    output y;

    assign y = (~a & b & c) | (~b & c & ~d) | (a & b & d);
endmodule

expressions/exp2/exp2_tb.v
module exp2_tb;
    reg a,b,c,d;
    wire y;

    exp2 uut(a,b,c,d,y);

    initial begin
        
        $dumpfile("exp2_wave.vcd");
        $dumpvars(0,exp2_tb);

        a = 0; b = 0; c = 0; d = 0; #5;
        a = 0; b = 0; c = 0; d = 1; #5;
        a = 0; b = 0; c = 1; d = 0; #5;
        a = 0; b = 0; c = 1; d = 1; #5;
        a = 0; b = 1; c = 0; d = 0; #5;
        a = 0; b = 1; c = 0; d = 1; #5;
        a = 0; b = 1; c = 1; d = 0; #5;
        a = 0; b = 1; c = 1; d = 1; #5;
        a = 1; b = 0; c = 0; d = 0; #5;
        a = 1; b = 0; c = 0; d = 1; #5;
        a = 1; b = 0; c = 1; d = 0; #5;
        a = 1; b = 0; c = 1; d = 1; #5;
        a = 1; b = 1; c = 0; d = 0; #5;
        a = 1; b = 1; c = 0; d = 1; #5;
        a = 1; b = 1; c = 1; d = 0; #5;
        a = 1; b = 1; c = 1; d = 1; #5;
        $finish;
    end

    initial begin
        $monitor("a = %b | b = %b | c = %b | d = %b | y = %b",a,b,c,d,y);
    end

endmodule

expressions/exp2/exp2_wave.vcd
$date
	Fri Dec 19 10:47:31 2025
$end
$version
	Icarus Verilog
$end
$timescale
	1s
$end
$scope module exp2_tb $end
$var wire 1 ! y $end
$var reg 1 " a $end
$var reg 1 # b $end
$var reg 1 $ c $end
$var reg 1 % d $end
$scope module uut $end
$var wire 1 " a $end
$var wire 1 # b $end
$var wire 1 $ c $end
$var wire 1 % d $end
$var wire 1 ! y $end
$upscope $end
$upscope $end
$enddefinitions $end
$comment Show the parameter values. $end
$dumpall
$end
#0
$dumpvars
0%
0$
0#
0"
0!
$end
#5
1%
#10
1!
0%
1$
#15
0!
1%
#20
0%
0$
1#
#25
1%
#30
1!
0%
1$
#35
1%
#40
0!
0%
0$
0#
1"
#45
1%
#50
1!
0%
1$
#55
0!
1%
#60
0%
0$
1#
#65
1!
1%
#70
0!
0%
1$
#75
1!
1%
