tri_state_mux/tri_state_mux.v
module tri_state_mux (
    in0,in1,select,out
);
    input in0,in1,select;
    output tri out;

    assign out = select? in1: in0;
    
endmodule

tri_state_mux/tri_state_mux_tb.v
module tri_state_mux_tb;
    reg in0, in1, select;
    wire out;

    tri_state_mux uut(in0,in1,select,out);

    initial begin
        $dumpfile("tri_state_mux_wave.vcd");
        $dumpvars(0,tri_state_mux_tb);

        $monitor("in0 = %b | in1 = %b | select = %b | out = %b",in0,in1,select,out);

        in0 = 0; in1 = 0; select = 0; #5;
        in0 = 0; in1 = 0; select = 1; #5;
        in0 = 0; in1 = 1; select = 0; #5;
        in0 = 0; in1 = 1; select = 1; #5;
        in0 = 1; in1 = 0; select = 0; #5;
        in0 = 1; in1 = 0; select = 1; #5;
        in0 = 1; in1 = 1; select = 0; #5;
        in0 = 1; in1 = 1; select = 1; #5;

        $finish;

    end
endmodule

tri_state_mux/tri_state_mux_wave.vcd
$date
	Sat Jan 24 20:07:47 2026
$end
$version
	Icarus Verilog
$end
$timescale
	1s
$end
$scope module tri_state_mux_tb $end
$var wire 1 ! out $end
$var reg 1 " in0 $end
$var reg 1 # in1 $end
$var reg 1 $ select $end
$scope module uut $end
$var wire 1 " in0 $end
$var wire 1 # in1 $end
$var wire 1 $ select $end
$var wire 1 ! out $end
$upscope $end
$upscope $end
$enddefinitions $end
$comment Show the parameter values. $end
$dumpall
$end
#0
$dumpvars
0$
0#
0"
0!
$end
#5
1$
#10
0$
1#
#15
1!
1$
#20
0$
0#
1"
#25
0!
1$
#30
1!
0$
1#
#35
1$
