full_adder/full_adder.v
module full_adder (
    a,b,cin,sum,cout
);

    input a,b,cin;
    output sum,cout;

    assign sum = a ^ b ^ cin;
    assign cout = (a*b) | (b*cin) | (a*cin);
    
endmodule

adders/full_adder/full_adder_tb.v
module full_adder_tb;
    reg a, b, cin;
    wire sum, cout;

    full_adder uut (
        .a(a),
        .b(b),
        .cin(cin),
        .sum(sum),
        .cout(cout)
    );

    initial begin
        $dumpfile("full_adder_wave.vcd");
        $dumpvars(0, full_adder_tb);

        $monitor("a = %b | b = %b | cin = %b | sum = %b | cout = %b", a, b,
                 cin, sum, cout);

        a   = 0;
        b   = 0;
        cin = 0;
        #5;
        a   = 0;
        b   = 0;
        cin = 1;
        #5;
        a   = 0;
        b   = 1;
        cin = 0;
        #5;
        a   = 0;
        b   = 1;
        cin = 1;
        #5;
        a   = 1;
        b   = 0;
        cin = 0;
        #5;
        a   = 1;
        b   = 0;
        cin = 1;
        #5;
        a   = 1;
        b   = 1;
        cin = 0;
        #5;
        a   = 1;
        b   = 1;
        cin = 1;
        #5;

        $finish;
    end
endmodule

full_adder/full_adder_wave.vcd
$date
	Thu Dec 18 12:07:08 2025
$end
$version
	Icarus Verilog
$end
$timescale
	1s
$end
$scope module full_adder_tb $end
$var wire 1 ! sum $end
$var wire 1 " cout $end
$var reg 1 # a $end
$var reg 1 $ b $end
$var reg 1 % cin $end
$scope module uut $end
$var wire 1 # a $end
$var wire 1 $ b $end
$var wire 1 % cin $end
$var wire 1 " cout $end
$var wire 1 ! sum $end
$upscope $end
$upscope $end
$enddefinitions $end
$comment Show the parameter values. $end
$dumpall
$end
#0
$dumpvars
0%
0$
0#
0"
0!
$end
#5
1!
1%
#10
0%
1$
#15
1"
0!
1%
#20
0"
1!
0%
0$
1#
#25
0!
1"
1%
#30
0%
1$
#35
1!
1%
